mergem/__database_processing.py
mergem/__init__.py
mergem/__merge_models.py
mergem/__model_handling.py
mergem/__version.py
mergem/cli.py
mergem/data/metaboliteIdMapper.p
mergem/data/metaboliteInfo.p
mergem/data/reactionIdMapper.p
mergem/data/reactionInfo.p
mergem-1.1.0.dist-info/LICENSE
mergem-1.1.0.dist-info/METADATA
mergem-1.1.0.dist-info/WHEEL
mergem-1.1.0.dist-info/entry_points.txt
mergem-1.1.0.dist-info/top_level.txt
mergem-1.1.0.dist-info/RECORD
