Metadata-Version: 2.1
Name: mergem
Version: 1.1.0
Summary: mergem is a python package and command-line tool for merging, comparing, and translating genome-scale metabolic models.
Home-page: https://lobolab.umbc.edu/mergem/
Author: Lobo Lab
Author-email: lobolab@umbc.edu
Maintainer: Archana Hari
Maintainer-email: archh1@umbc.edu
License: GNU GPLv3
Classifier: Programming Language :: Python :: 3
Classifier: License :: OSI Approved :: GNU General Public License (GPL)
Classifier: Operating System :: OS Independent
Classifier: Intended Audience :: Science/Research
Classifier: Development Status :: 4 - Beta
Classifier: Topic :: Scientific/Engineering
Classifier: Topic :: Scientific/Engineering :: Bio-Informatics
License-File: LICENSE
Requires-Dist: cobra >=0.15.4
Requires-Dist: click >=8.0.3
Requires-Dist: requests
